vkconnections/APIKeys.py
vkconnections/FirstLevel.py
vkconnections/Helper.py
vkconnections/SecondLevel.py
vkconnections/VkAPI.py
vkconnections/__init__.py
vkconnections/main.py
vkconnections-0.0.8.dist-info/LICENSE
vkconnections-0.0.8.dist-info/METADATA
vkconnections-0.0.8.dist-info/WHEEL
vkconnections-0.0.8.dist-info/top_level.txt
vkconnections-0.0.8.dist-info/RECORD
