Metadata-Version: 2.1
Name: vkconnections
Version: 0.0.8
Summary: Finding the shortest path from one vk user to another through friends.
Home-page: https://github.com/AndreyVolkovBI/VkConnections
Author: Andrey Volkov
Author-email: andrey@volkov.tech
License: UNKNOWN
Platform: UNKNOWN
Classifier: Programming Language :: Python :: 3
Classifier: License :: OSI Approved :: MIT License
Classifier: Operating System :: OS Independent
